miyadaiku_theme_newblog/__init__.py
miyadaiku_theme_newblog/config.yml
miyadaiku_theme_newblog/contents/about.md
miyadaiku_theme_newblog/contents/atom.yml
miyadaiku_theme_newblog/contents/index.yml
miyadaiku_theme_newblog/contents/index_tag.yml
miyadaiku_theme_newblog/contents/rss.yml
miyadaiku_theme_newblog/files/static/newblog/ipynb_styles.css
miyadaiku_theme_newblog/files/static/newblog/main.css
miyadaiku_theme_newblog/templates/base.html
miyadaiku_theme_newblog/templates/page_article.html
miyadaiku_theme_newblog/templates/page_index.html
miyadaiku_theme_newblog-1.13.0.dist-info/METADATA
miyadaiku_theme_newblog-1.13.0.dist-info/WHEEL
miyadaiku_theme_newblog-1.13.0.dist-info/top_level.txt
miyadaiku_theme_newblog-1.13.0.dist-info/RECORD
